[
    {
        "image": "https://i.ibb.co/qNnhK13/1.jpg",
        "room_description": "Luxury Suite with Ocean View",
        "price_per_night": "$300",
        "room_size": "700 sqft",
        "availability": true,
        "special_offers": "Complimentary breakfast included",
        "rating": 4.5
    },
    {
        "image": "https://i.ibb.co/4ZdQMXC/2.jpg",
        "room_description": "Standard Double Room",
        "price_per_night": "$200",
        "room_size": "400 sqft",
        "availability": false,
        "special_offers": "No",
        "rating": 4.0
    },
    {
        "image": "https://i.ibb.co/4ZK2ZpM/3.jpg",
        "room_description": "Executive Suite with City View",
        "price_per_night": "$100",
        "room_size": "600 sqft",
        "availability": true,
        "special_offers": "10% discount for stays longer than 3 nights",
        "rating": 4.8
    },
    {
        "image": "https://i.ibb.co/3BnXn16/4.jpg",
        "room_description": "Family Suite with Garden Access",
        "price_per_night": "$80",
        "room_size": "900 sqft",
        "availability": true,
        "special_offers": "No",
        "rating": 4.6
    },
    {
        "image": "https://i.ibb.co/y84qpcd/5.jpg",
        "room_description": "Deluxe Single Room",
        "price_per_night": "$150",
        "room_size": "300 sqft",
        "availability": true,
        "special_offers": "Free airport shuttle service",
        "rating": 4.2
    },
    {
        "image": "https://i.ibb.co/CVTTTrn/6.jpg",
        "room_description": "Penthouse Suite with Private Terrace",
        "price_per_night": "$120",
        "room_size": "1200 sqft",
        "availability": false,
        "special_offers": "No",
        "rating": 4.9
    },
    {
        "image": "https://i.ibb.co/fSWwtkL/7.jpg",
        "room_description": "Budget Single Room",
        "price_per_night": "$100",
        "room_size": "200 sqft",
        "availability": true,
        "special_offers": "50% off on weekdays",
        "rating": 3.9
    },
    {
        "image": "https://i.ibb.co/bvHkL8g/8.jpg",
        "room_description": "King Suite with Jacuzzi",
        "price_per_night": "$400",
        "room_size": "1000 sqft",
        "availability": true,
        "special_offers": "Complimentary bottle of champagne",
        "rating": 4.7
    },
    {
        "image": "https://i.ibb.co/tpnPHNS/9.jpg",
        "room_description": "Cozy Twin Room",
        "price_per_night": "$130",
        "room_size": "350 sqft",
        "availability": true,
        "special_offers": "No",
        "rating": 4.1
    }
]
